odoo/addons/partner_age/README.rst
odoo/addons/partner_age/__init__.py
odoo/addons/partner_age/__manifest__.py
odoo/addons/partner_age/i18n/partner_age.pot
odoo/addons/partner_age/models/__init__.py
odoo/addons/partner_age/models/partner.py
odoo/addons/partner_age/readme/CONTRIBUTORS.rst
odoo/addons/partner_age/readme/DESCRIPTION.rst
odoo/addons/partner_age/static/description/index.html
odoo/addons/partner_age/view/partner_view.xml
odoo12_addon_partner_age-12.0.2.0.0.99.dev6.dist-info/METADATA
odoo12_addon_partner_age-12.0.2.0.0.99.dev6.dist-info/WHEEL
odoo12_addon_partner_age-12.0.2.0.0.99.dev6.dist-info/top_level.txt
odoo12_addon_partner_age-12.0.2.0.0.99.dev6.dist-info/RECORD
