Metadata-Version: 2.1
Name: odoo12-addon-partner-age
Version: 12.0.2.0.0.99.dev6
Summary: This module computes the age of the partner.
Home-page: https://coopiteasy.be
Author: Coop IT Easy SCRLfs
License: AGPL-3
Platform: UNKNOWN
Classifier: Programming Language :: Python
Classifier: Framework :: Odoo
Classifier: Framework :: Odoo :: 12.0
Classifier: License :: OSI Approved :: GNU Affero General Public License v3
Requires-Python: >=3.5
Requires-Dist: odoo12-addon-partner-contact-birthdate
Requires-Dist: odoo (<12.1dev,>=12.0a)
